{
  "timestamp": "8:24 PM PT | May 20, 2026",
  "report_period": "evening",
  "generated_at": "2026-05-21T03:24:32.865103+00:00Z",
  "stations": [
    {
      "display": "Lakewood, WA",
      "emoji": "\ud83c\udf32",
      "name": "Lakewood",
      "state": "WA",
      "temp": 64,
      "feels_like": 62,
      "temp_high": 78,
      "temp_low": 49,
      "humidity": 57,
      "wind_speed": 6,
      "wind_dir": "N",
      "description": "Clear Sky",
      "uv_index": 6,
      "visibility": 6.2,
      "pressure": 1020,
      "dew_point": 48,
      "cloud_cover": 0,
      "sunrise": "05:28 AM",
      "sunset": "08:45 PM",
      "heat_label": "Cool",
      "pop": 0,
      "nws_alerts": []
    },
    {
      "display": "Groveland, CA",
      "emoji": "\ud83c\udfd4",
      "name": "Groveland",
      "state": "CA",
      "temp": 66,
      "feels_like": 65,
      "temp_high": 83,
      "temp_low": 50,
      "humidity": 46,
      "wind_speed": 4,
      "wind_dir": "NNE",
      "description": "Clear Sky",
      "uv_index": 9,
      "visibility": 6.2,
      "pressure": 1014,
      "dew_point": 45,
      "cloud_cover": 2,
      "sunrise": "05:47 AM",
      "sunset": "08:08 PM",
      "heat_label": "Pleasant",
      "pop": 0,
      "nws_alerts": []
    },
    {
      "display": "Death Valley, CA",
      "emoji": "\ud83d\udd25",
      "name": "Death Valley",
      "state": "CA",
      "temp": 86,
      "feels_like": 83,
      "temp_high": 102,
      "temp_low": 68,
      "humidity": 9,
      "wind_speed": 3,
      "wind_dir": "S",
      "description": "Overcast Clouds",
      "uv_index": 9,
      "visibility": 6.2,
      "pressure": 1007,
      "dew_point": 20,
      "cloud_cover": 100,
      "sunrise": "05:37 AM",
      "sunset": "07:51 PM",
      "heat_label": "Warm",
      "pop": 0,
      "nws_alerts": []
    },
    {
      "display": "Reno, NV",
      "emoji": "\ud83c\udfb0",
      "name": "Reno",
      "state": "NV",
      "temp": 70,
      "feels_like": 68,
      "temp_high": 77,
      "temp_low": 48,
      "humidity": 31,
      "wind_speed": 6,
      "wind_dir": "NNW",
      "description": "Overcast Clouds",
      "uv_index": 9,
      "visibility": 6.2,
      "pressure": 1014,
      "dew_point": 38,
      "cloud_cover": 94,
      "sunrise": "05:41 AM",
      "sunset": "08:10 PM",
      "heat_label": "Pleasant",
      "pop": 0,
      "nws_alerts": []
    }
  ],
  "forecast": {}
}