{
  "timestamp": "9:57 PM PT | June 22, 2026",
  "report_period": "evening",
  "generated_at": "2026-06-23T04:57:42.921777+00:00Z",
  "stations": [
    {
      "display": "Lakewood, WA",
      "emoji": "\ud83c\udf32",
      "name": "Lakewood",
      "state": "WA",
      "temp": 68,
      "feels_like": 67,
      "temp_high": 86,
      "temp_low": 61,
      "humidity": 55,
      "wind_speed": 5,
      "wind_dir": "NE",
      "description": "Scattered Clouds",
      "uv_index": 7,
      "visibility": 6.2,
      "pressure": 1015,
      "dew_point": 51,
      "cloud_cover": 42,
      "sunrise": "05:14 AM",
      "sunset": "09:09 PM",
      "heat_label": "Pleasant",
      "pop": 0,
      "nws_alerts": []
    },
    {
      "display": "Groveland, CA",
      "emoji": "\ud83c\udfd4",
      "name": "Groveland",
      "state": "CA",
      "temp": 71,
      "feels_like": 70,
      "temp_high": 84,
      "temp_low": 61,
      "humidity": 53,
      "wind_speed": 5,
      "wind_dir": "ENE",
      "description": "Clear Sky",
      "uv_index": 11,
      "visibility": 6.2,
      "pressure": 1014,
      "dew_point": 53,
      "cloud_cover": 0,
      "sunrise": "05:39 AM",
      "sunset": "08:26 PM",
      "heat_label": "Pleasant",
      "pop": 0,
      "nws_alerts": []
    },
    {
      "display": "Death Valley, CA",
      "emoji": "\ud83d\udd25",
      "name": "Death Valley",
      "state": "CA",
      "temp": 86,
      "feels_like": 83,
      "temp_high": 109,
      "temp_low": 81,
      "humidity": 10,
      "wind_speed": 5,
      "wind_dir": "SSE",
      "description": "Clear Sky",
      "uv_index": 11,
      "visibility": 6.2,
      "pressure": 1007,
      "dew_point": 23,
      "cloud_cover": 1,
      "sunrise": "05:30 AM",
      "sunset": "08:09 PM",
      "heat_label": "Warm",
      "pop": 0,
      "nws_alerts": []
    },
    {
      "display": "Reno, NV",
      "emoji": "\ud83c\udfb0",
      "name": "Reno",
      "state": "NV",
      "temp": 78,
      "feels_like": 77,
      "temp_high": 94,
      "temp_low": 66,
      "humidity": 39,
      "wind_speed": 8,
      "wind_dir": "WSW",
      "description": "Few Clouds",
      "uv_index": 10,
      "visibility": 6.2,
      "pressure": 1015,
      "dew_point": 51,
      "cloud_cover": 14,
      "sunrise": "05:32 AM",
      "sunset": "08:30 PM",
      "heat_label": "Pleasant",
      "pop": 0,
      "nws_alerts": []
    }
  ],
  "forecast": {}
}