{
  "timestamp": "2:23 AM PT | June 06, 2026",
  "report_period": "evening",
  "generated_at": "2026-06-06T09:24:01.905221+00:00Z",
  "stations": [
    {
      "display": "Lakewood, WA",
      "emoji": "\ud83c\udf32",
      "name": "Lakewood",
      "state": "WA",
      "temp": 50,
      "feels_like": 50,
      "temp_high": 54,
      "temp_low": 50,
      "humidity": 86,
      "wind_speed": 2,
      "wind_dir": "SSE",
      "description": "Overcast Clouds",
      "uv_index": 6,
      "visibility": 6.2,
      "pressure": 1013,
      "dew_point": 46,
      "cloud_cover": 100,
      "sunrise": "05:15 AM",
      "sunset": "09:02 PM",
      "heat_label": "Cold",
      "pop": 100,
      "nws_alerts": []
    },
    {
      "display": "Groveland, CA",
      "emoji": "\ud83c\udfd4",
      "name": "Groveland",
      "state": "CA",
      "temp": 58,
      "feels_like": 57,
      "temp_high": 75,
      "temp_low": 50,
      "humidity": 80,
      "wind_speed": 6,
      "wind_dir": "ENE",
      "description": "Clear Sky",
      "uv_index": 9,
      "visibility": 6.2,
      "pressure": 1010,
      "dew_point": 52,
      "cloud_cover": 0,
      "sunrise": "05:39 AM",
      "sunset": "08:20 PM",
      "heat_label": "Cool",
      "pop": 0,
      "nws_alerts": []
    },
    {
      "display": "Death Valley, CA",
      "emoji": "\ud83d\udd25",
      "name": "Death Valley",
      "state": "CA",
      "temp": 77,
      "feels_like": 75,
      "temp_high": 104,
      "temp_low": 77,
      "humidity": 22,
      "wind_speed": 4,
      "wind_dir": "ENE",
      "description": "Clear Sky",
      "uv_index": 10,
      "visibility": 6.2,
      "pressure": 1001,
      "dew_point": 35,
      "cloud_cover": 0,
      "sunrise": "05:29 AM",
      "sunset": "08:03 PM",
      "heat_label": "Pleasant",
      "pop": 0,
      "nws_alerts": []
    },
    {
      "display": "Reno, NV",
      "emoji": "\ud83c\udfb0",
      "name": "Reno",
      "state": "NV",
      "temp": 69,
      "feels_like": 66,
      "temp_high": 80,
      "temp_low": 48,
      "humidity": 29,
      "wind_speed": 19,
      "wind_dir": "WSW",
      "description": "Overcast Clouds",
      "uv_index": 9,
      "visibility": 6.2,
      "pressure": 1011,
      "dew_point": 35,
      "cloud_cover": 100,
      "sunrise": "05:32 AM",
      "sunset": "08:23 PM",
      "heat_label": "Pleasant",
      "pop": 0,
      "nws_alerts": []
    }
  ],
  "forecast": {}
}