{
  "timestamp": "2:30 PM PT | March 11, 2026",
  "report_period": "evening",
  "generated_at": "2026-03-11T21:30:58.846443+00:00Z",
  "stations": [
    {
      "display": "Lakewood, WA",
      "emoji": "\ud83c\udf32",
      "name": "Lakewood",
      "state": "WA",
      "temp": 48,
      "feels_like": 40,
      "temp_high": 50,
      "temp_low": 40,
      "humidity": 92,
      "wind_speed": 20,
      "wind_dir": "S",
      "description": "Moderate Rain",
      "uv_index": 2,
      "visibility": 4.0,
      "pressure": 1016,
      "dew_point": 45,
      "cloud_cover": 100,
      "sunrise": "07:30 AM",
      "sunset": "07:09 PM",
      "heat_label": "Cold",
      "pop": 100,
      "nws_alerts": []
    },
    {
      "display": "Groveland, CA",
      "emoji": "\ud83c\udfd4",
      "name": "Groveland",
      "state": "CA",
      "temp": 68,
      "feels_like": 66,
      "temp_high": 69,
      "temp_low": 49,
      "humidity": 38,
      "wind_speed": 7,
      "wind_dir": "W",
      "description": "Clear Sky",
      "uv_index": 5,
      "visibility": 6.2,
      "pressure": 1026,
      "dew_point": 41,
      "cloud_cover": 0,
      "sunrise": "07:18 AM",
      "sunset": "07:03 PM",
      "heat_label": "Pleasant",
      "pop": 0,
      "nws_alerts": []
    },
    {
      "display": "Death Valley, CA",
      "emoji": "\ud83d\udd25",
      "name": "Death Valley",
      "state": "CA",
      "temp": 86,
      "feels_like": 83,
      "temp_high": 89,
      "temp_low": 73,
      "humidity": 16,
      "wind_speed": 0,
      "wind_dir": "SSE",
      "description": "Clear Sky",
      "uv_index": 5,
      "visibility": 6.2,
      "pressure": 1022,
      "dew_point": 35,
      "cloud_cover": 0,
      "sunrise": "07:04 AM",
      "sunset": "06:51 PM",
      "heat_label": "Warm",
      "pop": 0,
      "nws_alerts": []
    },
    {
      "display": "Reno, NV",
      "emoji": "\ud83c\udfb0",
      "name": "Reno",
      "state": "NV",
      "temp": 64,
      "feels_like": 61,
      "temp_high": 67,
      "temp_low": 46,
      "humidity": 27,
      "wind_speed": 5,
      "wind_dir": "WNW",
      "description": "Broken Clouds",
      "uv_index": 5,
      "visibility": 6.2,
      "pressure": 1027,
      "dew_point": 29,
      "cloud_cover": 75,
      "sunrise": "07:16 AM",
      "sunset": "07:01 PM",
      "heat_label": "Cool",
      "pop": 0,
      "nws_alerts": []
    }
  ],
  "forecast": {}
}