{
  "timestamp": "2:23 AM PT | June 16, 2026",
  "report_period": "evening",
  "generated_at": "2026-06-16T09:23:20.705646+00:00Z",
  "stations": [
    {
      "display": "Lakewood, WA",
      "emoji": "\ud83c\udf32",
      "name": "Lakewood",
      "state": "WA",
      "temp": 62,
      "feels_like": 60,
      "temp_high": 73,
      "temp_low": 48,
      "humidity": 38,
      "wind_speed": 5,
      "wind_dir": "SW",
      "description": "Clear Sky",
      "uv_index": 9,
      "visibility": 6.2,
      "pressure": 1017,
      "dew_point": 36,
      "cloud_cover": 1,
      "sunrise": "05:13 AM",
      "sunset": "09:07 PM",
      "heat_label": "Cool",
      "pop": 0,
      "nws_alerts": []
    },
    {
      "display": "Groveland, CA",
      "emoji": "\ud83c\udfd4",
      "name": "Groveland",
      "state": "CA",
      "temp": 65,
      "feels_like": 65,
      "temp_high": 86,
      "temp_low": 62,
      "humidity": 74,
      "wind_speed": 5,
      "wind_dir": "ENE",
      "description": "Clear Sky",
      "uv_index": 10,
      "visibility": 6.2,
      "pressure": 1014,
      "dew_point": 56,
      "cloud_cover": 0,
      "sunrise": "05:38 AM",
      "sunset": "08:24 PM",
      "heat_label": "Cool",
      "pop": 0,
      "nws_alerts": []
    },
    {
      "display": "Death Valley, CA",
      "emoji": "\ud83d\udd25",
      "name": "Death Valley",
      "state": "CA",
      "temp": 82,
      "feels_like": 80,
      "temp_high": 111,
      "temp_low": 82,
      "humidity": 15,
      "wind_speed": 1,
      "wind_dir": "ESE",
      "description": "Clear Sky",
      "uv_index": 10,
      "visibility": 6.2,
      "pressure": 1008,
      "dew_point": 30,
      "cloud_cover": 0,
      "sunrise": "05:29 AM",
      "sunset": "08:07 PM",
      "heat_label": "Warm",
      "pop": 0,
      "nws_alerts": []
    },
    {
      "display": "Reno, NV",
      "emoji": "\ud83c\udfb0",
      "name": "Reno",
      "state": "NV",
      "temp": 71,
      "feels_like": 69,
      "temp_high": 95,
      "temp_low": 67,
      "humidity": 36,
      "wind_speed": 5,
      "wind_dir": "NNE",
      "description": "Clear Sky",
      "uv_index": 11,
      "visibility": 6.2,
      "pressure": 1020,
      "dew_point": 42,
      "cloud_cover": 1,
      "sunrise": "05:31 AM",
      "sunset": "08:28 PM",
      "heat_label": "Pleasant",
      "pop": 0,
      "nws_alerts": []
    }
  ],
  "forecast": {}
}