{
  "timestamp": "4:36 PM PT | April 17, 2026",
  "report_period": "evening",
  "generated_at": "2026-04-17T23:37:09.589483+00:00Z",
  "stations": [
    {
      "display": "Lakewood, WA",
      "emoji": "\ud83c\udf32",
      "name": "Lakewood",
      "state": "WA",
      "temp": 56,
      "feels_like": 54,
      "temp_high": 66,
      "temp_low": 42,
      "humidity": 50,
      "wind_speed": 12,
      "wind_dir": "WNW",
      "description": "Few Clouds",
      "uv_index": 5,
      "visibility": 6.2,
      "pressure": 1022,
      "dew_point": 38,
      "cloud_cover": 20,
      "sunrise": "06:17 AM",
      "sunset": "08:00 PM",
      "heat_label": "Cool",
      "pop": 0,
      "nws_alerts": []
    },
    {
      "display": "Groveland, CA",
      "emoji": "\ud83c\udfd4",
      "name": "Groveland",
      "state": "CA",
      "temp": 66,
      "feels_like": 64,
      "temp_high": 69,
      "temp_low": 47,
      "humidity": 41,
      "wind_speed": 1,
      "wind_dir": "WNW",
      "description": "Few Clouds",
      "uv_index": 7,
      "visibility": 6.2,
      "pressure": 1016,
      "dew_point": 41,
      "cloud_cover": 12,
      "sunrise": "06:22 AM",
      "sunset": "07:37 PM",
      "heat_label": "Pleasant",
      "pop": 0,
      "nws_alerts": []
    },
    {
      "display": "Death Valley, CA",
      "emoji": "\ud83d\udd25",
      "name": "Death Valley",
      "state": "CA",
      "temp": 76,
      "feels_like": 74,
      "temp_high": 84,
      "temp_low": 64,
      "humidity": 4,
      "wind_speed": 5,
      "wind_dir": "WNW",
      "description": "Clear Sky",
      "uv_index": 6,
      "visibility": 6.2,
      "pressure": 1015,
      "dew_point": -4,
      "cloud_cover": 0,
      "sunrise": "06:11 AM",
      "sunset": "07:23 PM",
      "heat_label": "Pleasant",
      "pop": 0,
      "nws_alerts": []
    },
    {
      "display": "Reno, NV",
      "emoji": "\ud83c\udfb0",
      "name": "Reno",
      "state": "NV",
      "temp": 58,
      "feels_like": 54,
      "temp_high": 63,
      "temp_low": 36,
      "humidity": 15,
      "wind_speed": 9,
      "wind_dir": "NE",
      "description": "Few Clouds",
      "uv_index": 7,
      "visibility": 6.2,
      "pressure": 1016,
      "dew_point": 10,
      "cloud_cover": 20,
      "sunrise": "06:18 AM",
      "sunset": "07:38 PM",
      "heat_label": "Cool",
      "pop": 0,
      "nws_alerts": []
    }
  ],
  "forecast": {}
}