{
  "timestamp": "10:22 PM PT | April 09, 2026",
  "report_period": "evening",
  "generated_at": "2026-04-10T05:23:13.643185+00:00Z",
  "stations": [
    {
      "display": "Lakewood, WA",
      "emoji": "\ud83c\udf32",
      "name": "Lakewood",
      "state": "WA",
      "temp": 50,
      "feels_like": 48,
      "temp_high": 71,
      "temp_low": 44,
      "humidity": 74,
      "wind_speed": 3,
      "wind_dir": "NNE",
      "description": "Scattered Clouds",
      "uv_index": 5,
      "visibility": 6.2,
      "pressure": 1012,
      "dew_point": 42,
      "cloud_cover": 35,
      "sunrise": "06:32 AM",
      "sunset": "07:49 PM",
      "heat_label": "Cool",
      "pop": 0,
      "nws_alerts": []
    },
    {
      "display": "Groveland, CA",
      "emoji": "\ud83c\udfd4",
      "name": "Groveland",
      "state": "CA",
      "temp": 56,
      "feels_like": 55,
      "temp_high": 57,
      "temp_low": 48,
      "humidity": 83,
      "wind_speed": 4,
      "wind_dir": "ENE",
      "description": "Very Heavy Rain",
      "uv_index": 6,
      "visibility": 6.2,
      "pressure": 1012,
      "dew_point": 51,
      "cloud_cover": 95,
      "sunrise": "06:33 AM",
      "sunset": "07:30 PM",
      "heat_label": "Cool",
      "pop": 100,
      "nws_alerts": []
    },
    {
      "display": "Death Valley, CA",
      "emoji": "\ud83d\udd25",
      "name": "Death Valley",
      "state": "CA",
      "temp": 81,
      "feels_like": 80,
      "temp_high": 88,
      "temp_low": 75,
      "humidity": 26,
      "wind_speed": 9,
      "wind_dir": "SSE",
      "description": "Overcast Clouds",
      "uv_index": 7,
      "visibility": 6.2,
      "pressure": 1005,
      "dew_point": 43,
      "cloud_cover": 99,
      "sunrise": "06:21 AM",
      "sunset": "07:16 PM",
      "heat_label": "Warm",
      "pop": 0,
      "nws_alerts": []
    },
    {
      "display": "Reno, NV",
      "emoji": "\ud83c\udfb0",
      "name": "Reno",
      "state": "NV",
      "temp": 52,
      "feels_like": 50,
      "temp_high": 57,
      "temp_low": 44,
      "humidity": 80,
      "wind_speed": 6,
      "wind_dir": "W",
      "description": "Overcast Clouds",
      "uv_index": 6,
      "visibility": 6.2,
      "pressure": 1014,
      "dew_point": 46,
      "cloud_cover": 100,
      "sunrise": "06:30 AM",
      "sunset": "07:30 PM",
      "heat_label": "Cool",
      "pop": 95,
      "nws_alerts": []
    }
  ],
  "forecast": {}
}